{"id":32424,"path":"Assets\/Game_Play\/Prefaps\/In_Game\/Common\/Health_Bar\/Health_Bar.prefab","assetBundleId":-1,"components":[{"type":2,"id":31088,"data":[0,0.600000023841858,0,1,1,1,0,0,0,1]},{"type":3,"id":31116,"enabled":1,"class":45,"data":[1,100,35,0,0,2,32400,null,null,17,32450,17,32434,2,32414,17,32390,17,32388]},{"type":3,"id":33388,"enabled":1,"class":60,"data":[0,0,0,2,32404,17,33402,17,33872]}],"children":[{"id":32450,"path":"Assets\/Game_Play\/Prefaps\/In_Game\/Common\/Health_Bar\/Health_Bar.prefab","assetBundleId":-1,"components":[{"type":2,"id":32440,"data":[0,0,0,1,1,1,0,0,0,1]},{"type":42,"id":33380,"data":[1,7,556,[7,556],0,0,0,-5,-1,-1,1,1,0,0,1,1,1,1,1,1,15,30904,0,0,1,1,0.200000002980232,0,0.5,0,0]}],"children":[],"data":["BG",0,1,0,0]},{"id":32434,"path":"Assets\/Game_Play\/Prefaps\/In_Game\/Common\/Health_Bar\/Health_Bar.prefab","assetBundleId":-1,"components":[{"type":2,"id":32400,"data":[-0.485000014305115,0,0,1,1,1,0,0,0,1]}],"children":[{"id":33888,"path":"Assets\/Game_Play\/Prefaps\/In_Game\/Common\/Health_Bar\/Health_Bar.prefab","assetBundleId":-1,"components":[{"type":2,"id":33376,"data":[0.485000014305115,0,0,1,1,1,0,0,0,1]},{"type":42,"id":34142,"data":[1,7,556,[7,556],0,0,0,-4,-1,-1,1,1,0,0,1,1,0.153887018561363,0.745283007621765,0.0246084146201611,1,15,30918,0,0,1,0.97006893157959,0.200000002980232,0,0.5,0,0]}],"children":[],"data":["Model",0,1,0,0]}],"data":["Progress",0,1,0,0]},{"id":33402,"path":"Assets\/Game_Play\/Prefaps\/In_Game\/Common\/Health_Bar\/Health_Bar.prefab","assetBundleId":-1,"components":[{"type":2,"id":32442,"data":[0,-0.118600003421307,0,1,1,1,0,0,0,1]},{"type":42,"id":33894,"data":[1,7,556,[7,556],0,0,0,11,-1,-1,1,1,0,0,1,1,0,0,0,1,15,30904,0,0,1,1,0.0332746431231499,0,0.5,0,0]}],"children":[],"data":["BG_Exp",0,1,0,0]},{"id":33374,"path":"Assets\/Game_Play\/Prefaps\/In_Game\/Common\/Health_Bar\/Health_Bar.prefab","assetBundleId":-1,"components":[{"type":2,"id":32404,"data":[-0.5,-0.118600003421307,0,0.300000011920929,1,1,0,0,0,1]}],"children":[{"id":33872,"path":"Assets\/Game_Play\/Prefaps\/In_Game\/Common\/Health_Bar\/Health_Bar.prefab","assetBundleId":-1,"components":[{"type":2,"id":33420,"data":[0.5,0,0,1,1,1,0,0,0,1]},{"type":42,"id":34170,"data":[1,7,556,[7,556],0,0,0,12,-1,-1,1,1,0,0,1,1,1,0.567994236946106,0,1,15,30904,0,0,1,1,0.0332746393978596,0,0.5,0,0]}],"children":[],"data":["Model",0,1,0,0]}],"data":["Progress_Exp",0,1,0,0]},{"id":32390,"path":"Assets\/Game_Play\/Prefaps\/In_Game\/Common\/Health_Bar\/Health_Bar.prefab","assetBundleId":-1,"components":[{"type":2,"id":32386,"data":[0,0.200000002980232,0,1,1,1,0,0,0,1]},{"type":42,"id":33406,"data":[1,7,556,[7,556],0,0,0,-5,-1,-1,1,1,0,0,1,1,1,1,1,1,15,30904,0,0,1,1,0.200000002980232,0,0.5,0,0]}],"children":[],"data":["BG2",0,0,0,0]},{"id":32388,"path":"Assets\/Game_Play\/Prefaps\/In_Game\/Common\/Health_Bar\/Health_Bar.prefab","assetBundleId":-1,"components":[{"type":2,"id":32414,"data":[-0.485000014305115,0.200000002980232,0,1,1,1,0,0,0,1]}],"children":[{"id":33866,"path":"Assets\/Game_Play\/Prefaps\/In_Game\/Common\/Health_Bar\/Health_Bar.prefab","assetBundleId":-1,"components":[{"type":2,"id":33370,"data":[0.485000014305115,0,0,1,1,1,0,0,0,1]},{"type":42,"id":34144,"data":[1,7,556,[7,556],0,0,0,-4,-1,-1,1,1,0,0,1,1,0.339622616767883,0.339622616767883,0.339622616767883,1,15,30918,0,0,1,0.97006893157959,0.200000002980232,0,0.5,0,0]}],"children":[],"data":["Model",0,1,0,0]}],"data":["Progress FAKE",0,0,0,0]}],"data":["Health_Bar",0,1,0,0]}